[
  {
    "command": "schema:generate:field",
    "plugin": "@salesforce/plugin-sobject",
    "flags": ["label", "object"],
    "alias": ["generate:metadata:field"]
  },
  {
    "command": "schema:generate:platformevent",
    "plugin": "@salesforce/plugin-sobject",
    "flags": ["label"],
    "alias": ["generate:metadata:platformevent"]
  },
  {
    "command": "schema:generate:sobject",
    "plugin": "@salesforce/plugin-sobject",
    "flags": ["label", "use-default-features"],
    "alias": ["generate:metadata:sobject"]
  },
  {
    "command": "schema:generate:tab",
    "plugin": "@salesforce/plugin-sobject",
    "flags": ["directory", "icon", "json", "object"],
    "alias": ["generate:metadata:tab"]
  }
]
